CHANGES
MANIFEST.in
README
setup.py
django_whatsnew.egg-info/PKG-INFO
django_whatsnew.egg-info/SOURCES.txt
django_whatsnew.egg-info/dependency_links.txt
django_whatsnew.egg-info/top_level.txt
whatsnew/__init__.py
whatsnew/admin.py
whatsnew/fields.py
whatsnew/models.py
whatsnew/tests.py
whatsnew/urls.py
whatsnew/util.py
whatsnew/version.py
whatsnew/views.py
whatsnew/migrations/0001_initial.py
whatsnew/migrations/0002_auto_20140808_0547.py
whatsnew/migrations/__init__.py
whatsnew/south_migrations/0001_initial.py
whatsnew/south_migrations/0002_auto__add_field_whatsnew_released.py
whatsnew/south_migrations/0003_auto__chg_field_whatsnew_version.py
whatsnew/south_migrations/0004_auto__del_field_whatsnew_released__add_field_whatsnew_enabled__chg_fie.py
whatsnew/south_migrations/0005_auto__add_field_whatsnew_expire.py
whatsnew/south_migrations/0006_auto__add_field_whatsnew_date.py
whatsnew/south_migrations/0007_auto__add_field_whatsnew_order__chg_field_whatsnew_date.py
whatsnew/south_migrations/0008_auto__chg_field_whatsnew_order.py
whatsnew/south_migrations/__init__.py
whatsnew/static/whatsnew/js/jquery.bpopup.min.js
whatsnew/templates/admin/whatsnew/change_form_whatsnew.html
whatsnew/templates/whatsnew/changelog.html
whatsnew/templates/whatsnew/test.html
whatsnew/templates/whatsnew/whatsnew.html
whatsnew/templatetags/__init__.py
whatsnew/templatetags/whatsnew.py